<?xml version="1.0"?>

<PropertyList>
	<default>
		<menu n="10">
			<label>PZL-Koliber 160A</label>
			<enabled type="bool">true</enabled>

			<item>
				<label>Aircraft Options</label>
				<binding>
					<command>dialog-show</command>
					<dialog-name>aircraft-dialog</dialog-name>
				</binding>
			</item>

			<item>
				<label>Autostart</label>
				<binding>
					<command>nasal</command>
					<script>pzl_koliber_160a.autostart();</script>
				</binding>
			</item>
			<item>
				<label>Select Livery</label>
				<binding>
					<command>nasal</command>
					<script>aircraft.livery.dialog.open()</script>
				</binding>
			</item>
		</menu>

	</default>

</PropertyList>
